jilkpw_py/__init__.py
jilkpw_py/__main__.py
jilkpw_py/core.py
jilkpw_py/error_catch.py
jilkpw_py-1.0.3.dist-info/METADATA
jilkpw_py-1.0.3.dist-info/WHEEL
jilkpw_py-1.0.3.dist-info/top_level.txt
jilkpw_py-1.0.3.dist-info/RECORD
