Metadata-Version: 2.1
Name: jilkpw-py
Version: 1.0.3
Summary: Jilk.pw Python Wrapper is a small python module for connecting to Jilk.pw's Public API. This can help if you would like to embed items from your Discord Server into anything that binds with Python.
Home-page: https://gitlab.com/scOwez/jilkpw-python-wrapper
Author: scOwez
Author-email: owez@scalist.net
License: Apache
Platform: UNKNOWN
Classifier: License :: OSI Approved :: Apache Software License
Classifier: Operating System :: OS Independent
Classifier: Programming Language :: Python :: 3
